AuroraSolarClient/__init__.py
AuroraSolarClient/client.py
AuroraSolarClient-2.0.1.dist-info/LICENSE
AuroraSolarClient-2.0.1.dist-info/METADATA
AuroraSolarClient-2.0.1.dist-info/WHEEL
AuroraSolarClient-2.0.1.dist-info/top_level.txt
AuroraSolarClient-2.0.1.dist-info/RECORD
