Metadata-Version: 2.1
Name: AuroraSolarClient
Version: 2.0.1
Summary: A python client for Aurora Solar
Home-page: https://github.com/chaosinside/python-aurora-solar-client
Author: Chris Hubbard
Author-email: chubbard@gmail.com
License: UNKNOWN
Platform: UNKNOWN
Classifier: Programming Language :: Python :: 3
Classifier: License :: OSI Approved :: MIT License
Classifier: Operating System :: OS Independent
Requires-Python: >=3.6
Requires-Dist: requests
